unstract/adapters/__init__.py
unstract/adapters/adapterkit.py
unstract/adapters/base.py
unstract/adapters/constants.py
unstract/adapters/embedding/__init__.py
unstract/adapters/embedding/azure_open_ai/README.md
unstract/adapters/embedding/azure_open_ai/pyproject.toml
unstract/adapters/embedding/azure_open_ai/src/__init__.py
unstract/adapters/embedding/azure_open_ai/src/azure_open_ai.py
unstract/adapters/embedding/azure_open_ai/src/static/json_schema.json
unstract/adapters/embedding/embedding_adapter.py
unstract/adapters/embedding/helper.py
unstract/adapters/embedding/hugging_face/README.md
unstract/adapters/embedding/hugging_face/pyproject.toml
unstract/adapters/embedding/hugging_face/src/__init__.py
unstract/adapters/embedding/hugging_face/src/hugging_face.py
unstract/adapters/embedding/hugging_face/src/static/json_schema.json
unstract/adapters/embedding/ollama/README.md
unstract/adapters/embedding/ollama/pyproject.toml
unstract/adapters/embedding/ollama/src/__init__.py
unstract/adapters/embedding/ollama/src/ollama.py
unstract/adapters/embedding/ollama/src/static/json_schema.json
unstract/adapters/embedding/open_ai/README.md
unstract/adapters/embedding/open_ai/pyproject.toml
unstract/adapters/embedding/open_ai/src/__init__.py
unstract/adapters/embedding/open_ai/src/open_ai.py
unstract/adapters/embedding/open_ai/src/static/json_schema.json
unstract/adapters/embedding/palm/README.md
unstract/adapters/embedding/palm/pyproject.toml
unstract/adapters/embedding/palm/src/__init__.py
unstract/adapters/embedding/palm/src/palm.py
unstract/adapters/embedding/palm/src/static/json_schema.json
unstract/adapters/embedding/qdrant_fast_embed/README.md
unstract/adapters/embedding/qdrant_fast_embed/pyproject.toml
unstract/adapters/embedding/qdrant_fast_embed/src/__init__.py
unstract/adapters/embedding/qdrant_fast_embed/src/qdrant_fast_embed.py
unstract/adapters/embedding/qdrant_fast_embed/src/static/json_schema.json
unstract/adapters/embedding/register.py
unstract/adapters/enums.py
unstract_adapters-0.22.0.dist-info/METADATA
unstract_adapters-0.22.0.dist-info/WHEEL
unstract_adapters-0.22.0.dist-info/licenses/LICENSE
unstract_adapters-0.22.0.dist-info/RECORD
